my_sample_pkg/__init__.py
my_sample_pkg/main.py
my_sample_pkg-0.1.2.dist-info/licenses/LICENSE
my_sample_pkg-0.1.2.dist-info/METADATA
my_sample_pkg-0.1.2.dist-info/WHEEL
my_sample_pkg-0.1.2.dist-info/entry_points.txt
my_sample_pkg-0.1.2.dist-info/top_level.txt
my_sample_pkg-0.1.2.dist-info/RECORD
